cloudofficeprint/__init__.py
cloudofficeprint/exceptions.py
cloudofficeprint/printjob.py
cloudofficeprint/resource.py
cloudofficeprint/response.py
cloudofficeprint/template.py
cloudofficeprint/transformation.py
cloudofficeprint/config/__init__.py
cloudofficeprint/config/cloud.py
cloudofficeprint/config/csv.py
cloudofficeprint/config/output.py
cloudofficeprint/config/pdf.py
cloudofficeprint/config/request_option.py
cloudofficeprint/config/server.py
cloudofficeprint/elements/__init__.py
cloudofficeprint/elements/charts.py
cloudofficeprint/elements/codes.py
cloudofficeprint/elements/elements.py
cloudofficeprint/elements/form.py
cloudofficeprint/elements/images.py
cloudofficeprint/elements/loops.py
cloudofficeprint/elements/pdf.py
cloudofficeprint/elements/rest_source.py
cloudofficeprint/own_utils/__init__.py
cloudofficeprint/own_utils/file_utils.py
cloudofficeprint/own_utils/type_utils.py
cloudofficeprint-25.1.0.dist-info/METADATA
cloudofficeprint-25.1.0.dist-info/WHEEL
cloudofficeprint-25.1.0.dist-info/top_level.txt
cloudofficeprint-25.1.0.dist-info/RECORD
