Metadata-Version: 2.4
Name: cloudofficeprint
Version: 25.1.0
Summary: Python interface for Cloud Office Print
Home-page: https://github.com/United-Codes/cloudofficeprint-python
Author: United Codes
Author-email: info@united-codes.com
License: GNU
Classifier: Programming Language :: Python :: 3
Classifier: License :: OSI Approved :: GNU General Public License v3 (GPLv3)
Classifier: Operating System :: OS Independent
Requires-Python: >=3.7
Requires-Dist: requests
Requires-Dist: pandas
Dynamic: author
Dynamic: author-email
Dynamic: classifier
Dynamic: description
Dynamic: description-content-type
Dynamic: home-page
Dynamic: license
Dynamic: requires-dist
Dynamic: requires-python
Dynamic: summary
